README.md
setup.py
crash_vm/__init__.py
crash_vm/_types.py
crash_vm/asm.py
crash_vm/bus.py
crash_vm/cpu.py
crash_vm/ram.py
crash_vm/vm.py
crash_vm.egg-info/PKG-INFO
crash_vm.egg-info/SOURCES.txt
crash_vm.egg-info/dependency_links.txt
crash_vm.egg-info/top_level.txt