Metadata-Version: 1.2
Name: crash-vm
Version: 0.0.3
Summary: Simple virtual machine implemented in pure python
Home-page: https://github.com/hypafrag/crash-vm
License: UNKNOWN
Platform: UNKNOWN
Classifier: Programming Language :: Python :: 3
Classifier: Operating System :: OS Independent
Requires-Python: >=3.7
